Workbook
Name aporte: Planilha1!$C$22
Name patrimonio: Planilha1!$C$25
Name qtd_anos: Planilha1!$C$23
Name Rendimento_Carteira: Planilha1!$C$18
Name salario: Planilha1!$C$17
Name sug_invest: Planilha1!$C$19
Name taxa_mensal: Planilha1!$C$24

Sheet Planilha1
B16: Configurações
B17: Salário | C17: 3500
B18: Rendimento Carteira | C18: 0.012
B19: Sugestão de Investimento | C19: =C17*20% -> 700
B21: Investimento Mensal
B22: Quanto Investir por mês? | C22: 150
B23: Por Quantos Anos? | C23: 1
B24: Taxa de Rendimento mensal? | C24: 0.012
B25: Patrimônio acumulado? | C25: =FV(taxa_mensal,qtd_anos*12,aporte*-1) -> 1923.6828
B26: Dividendos Mensais? | C26: =C25*C24 -> 23.084194
B28: Cenários
B29: Quanto em 2 anos? | C29: =FV($C$24,2*12,$C$22*-1) -> 4143.41 | D29: =C29*Rendimento_Carteira -> 49.720921
B30: Quanto em 5 anos? | C30: =FV($C$24,5*12,$C$22*-1) -> 13070.591 | D30: =C30*Rendimento_Carteira -> 156.84709
B31: Quanto em 10 anos? | C31: =FV($C$24,10*12,$C$22*-1) -> 39808.409 | D31: =C31*Rendimento_Carteira -> 477.70091
B32: Quanto em12 anos? | C32: =FV($C$24,12*12,$C$22*-1) -> 57147.224 | D32: =C32*Rendimento_Carteira -> 685.76669
B35: Perfil | C35: conservador
B36: VALOR A SER INVESTIDO POR MÊS | C36: =aporte -> 150
B38: TIPO DE FII | C38: PERCENTUAL SUGERIDO | D38: VALORES
B39: PAPEL | C39: =VLOOKUP($C$35&"-"&B39,Planilha2!$A$5:$D$22,4,0) -> 0.3 | D39: =$C$36*C39 -> 45
B40: TIJOLO | C40: =VLOOKUP($C$35&"-"&B40,Planilha2!$A$5:$D$22,4,0) -> 0.5 | D40: =$C$36*C40 -> 75
B41: HIBRIDOS | C41: =VLOOKUP($C$35&"-"&B41,Planilha2!$A$5:$D$22,4,0) -> 0.1 | D41: =$C$36*C41 -> 15
B42: FOF'S | C42: =VLOOKUP($C$35&"-"&B42,Planilha2!$A$5:$D$22,4,0) -> 0.1 | D42: =$C$36*C42 -> 15
B43: DESENVOLVIMENTO | C43: =VLOOKUP($C$35&"-"&B43,Planilha2!$A$5:$D$22,4,0) -> 0 | D43: =$C$36*C43 -> 0
B44: HOTELARIAS | C44: =VLOOKUP($C$35&"-"&B44,Planilha2!$A$5:$D$22,4,0) -> 0 | D44: =$C$36*C44 -> 0
B45: TOTAL | D45: =SUM(D39:D44) -> 150

Sheet Planilha2
A4: CHAVE | B4: PERFIL | C4: TIPO DE FII | D4: % | H4: %
A5: =B5&"-"&C5 -> conservador-PAPEL | B5: conservador | C5: PAPEL | D5: 0.3 | G5: moderado-TIJOLO | H5: =VLOOKUP(G5,A5:D22,4,0) -> 0.4
A6: =B6&"-"&C6 -> conservador-TIJOLO | B6: conservador | C6: TIJOLO | D6: 0.5
A7: =B7&"-"&C7 -> conservador-HIBRIDOS | B7: conservador | C7: HIBRIDOS | D7: 0.1
A8: =B8&"-"&C8 -> conservador-FOF'S | B8: conservador | C8: FOF'S | D8: 0.1
A9: =B9&"-"&C9 -> conservador-DESENVOLVIMENTO | B9: conservador | C9: DESENVOLVIMENTO | D9: 0
A10: =B10&"-"&C10 -> conservador-HOTELARIAS | B10: conservador | C10: HOTELARIAS | D10: 0
A11: =B11&"-"&C11 -> moderado-PAPEL | B11: moderado | C11: PAPEL | D11: 0.32
A12: =B12&"-"&C12 -> moderado-TIJOLO | B12: moderado | C12: TIJOLO | D12: 0.4
A13: =B13&"-"&C13 -> moderado-HIBRIDOS | B13: moderado | C13: HIBRIDOS | D13: 0.08
A14: =B14&"-"&C14 -> moderado-FOF'S | B14: moderado | C14: FOF'S | D14: 0.1
A15: =B15&"-"&C15 -> moderado-DESENVOLVIMENTO | B15: moderado | C15: DESENVOLVIMENTO | D15: 0.05
A16: =B16&"-"&C16 -> moderado-HOTELARIAS | B16: moderado | C16: HOTELARIAS | D16: 0.05
A17: =B17&"-"&C17 -> agressivo-PAPEL | B17: agressivo | C17: PAPEL | D17: 0.4
... A22: =B22&"-"&C22 -> agressivo-HOTELARIAS | B22: agressivo | C22: HOTELARIAS | D22: 0.12
